kumir_compose/__init__.py
kumir_compose/__main__.py
kumir_compose/commands/__init__.py
kumir_compose/commands/common.py
kumir_compose/commands/compile.py
kumir_compose/commands/compose.py
kumir_compose/commands/depend.py
kumir_compose/commands/init.py
kumir_compose/commands/run.py
kumir_compose/commands/web.py
kumir_compose/config/__init__.py
kumir_compose/config/config_file.py
kumir_compose/decompiler/__init__.py
kumir_compose/decompiler/decompiler.py
kumir_compose/decompiler/exceptions.py
kumir_compose/decompiler/instructions.py
kumir_compose/kspi/__init__.py
kumir_compose/kspi/integrations/__init__.py
kumir_compose/kspi/integrations/http.py
kumir_compose/kspi/integrations/psql.py
kumir_compose/kspi/integrations/stdio.py
kumir_compose/kspi/kspi.py
kumir_compose/kspi/messages.py
kumir_compose/main.py
kumir_compose/packages/__init__.py
kumir_compose/packages/discover.py
kumir_compose/packages/disk_manager.py
kumir_compose/packages/downloader.py
kumir_compose/packages/exceptions.py
kumir_compose/packages/package_manager.py
kumir_compose/packages/resolver.py
kumir_compose/preprocessor/__init__.py
kumir_compose/preprocessor/char_range.py
kumir_compose/preprocessor/exceptions.py
kumir_compose/preprocessor/lexer.py
kumir_compose/preprocessor/preprocessor.py
kumir_compose/preprocessor/tokens.py
kumir_compose/utils/__init__.py
kumir_compose/utils/kcollections_adapter.py
kumir_compose/web/__init__.py
kumir_compose/web/config_file.py
kumir_compose/web/handler.py
kumir_compose/web/interfaces.py
kumir_compose/web/wsgi.py
kumir_compose-0.2.dist-info/entry_points.txt
kumir_compose-0.2.dist-info/METADATA
kumir_compose-0.2.dist-info/WHEEL
kumir_compose-0.2.dist-info/RECORD
