Metadata-Version: 2.3
Name: kumir-compose
Version: 0.2
Summary: Kumir preprocessing, package management and debugging tool
License: GNU GPL v3.0
Author: Tapeline
Author-email: yt.redstone.mail@gmail.com
Requires-Python: >=3.12,<4.0
Classifier: License :: Other/Proprietary License
Classifier: Programming Language :: Python :: 3
Classifier: Programming Language :: Python :: 3.12
Classifier: Programming Language :: Python :: 3.13
Requires-Dist: alive-progress (>=3.2.0,<4.0.0)
Requires-Dist: attrs (>=25.3.0,<26.0.0)
Requires-Dist: click (>=8.1.8,<9.0.0)
Requires-Dist: psycopg2-binary (>=2.9.10,<3.0.0)
Requires-Dist: pydantic (>=2.10.6,<3.0.0)
Requires-Dist: pygithub (>=2.6.1,<3.0.0)
Requires-Dist: pyyaml (>=6.0.2,<7.0.0)
Requires-Dist: requests (>=2.32.3,<3.0.0)
Requires-Dist: waitress (>=3.0.2,<4.0.0)
